tests/__init__.py
tests/test_string_compounds.py
tests/test_typo_case.py
typocase/__init__.py
typocase/models.py
typocase/string_compounds.py
typocase/typo_case.py
typocase-0.1.dist-info/LICENSE
typocase-0.1.dist-info/METADATA
typocase-0.1.dist-info/WHEEL
typocase-0.1.dist-info/top_level.txt
typocase-0.1.dist-info/RECORD
