Metadata-Version: 2.1
Name: typocase
Version: 0.1
Summary: Lightweight library written in idiomatic Python (no regular expressions), that aims to translate string into various typography conventions.
Home-page: https://github.com/mtovmassian/typocase
Author: Martin Tovmassian
Author-email: martin.tovmassian@protonmail.com
License: UNKNOWN
Platform: UNKNOWN
Classifier: Programming Language :: Python :: 3.8
Classifier: Development Status :: 3 - Alpha
Classifier: Intended Audience :: Developers
Classifier: Topic :: Software Development :: Build Tools
Classifier: License :: OSI Approved :: MIT License
